EnigmaAPI/__init__.py
enigmaapi-1.0.1.dist-info/METADATA
enigmaapi-1.0.1.dist-info/WHEEL
enigmaapi-1.0.1.dist-info/top_level.txt
enigmaapi-1.0.1.dist-info/RECORD
